LICENSE
README.md
setup.py
panel_com_g2/__init__.py
panel_com_g2/panel.py
panel_com_g2.egg-info/PKG-INFO
panel_com_g2.egg-info/SOURCES.txt
panel_com_g2.egg-info/dependency_links.txt
panel_com_g2.egg-info/requires.txt
panel_com_g2.egg-info/top_level.txt