Metadata-Version: 2.1
Name: panel-com-g2
Version: 0.2
Summary: Panel controller rewrite for Reiser's Generation 2 Panels.
Home-page: https://github.com/Nobelz/panel_com
Author: Nobel Zhou
Author-email: nxz157@case.edu
Project-URL: Issue Tracker, https://github.com/Nobelz/panel_com/issues
Classifier: Development Status :: 3 - Alpha
Classifier: Intended Audience :: Developers
Classifier: Topic :: Software Development
Classifier: Programming Language :: Python :: 2
Classifier: Programming Language :: Python :: 3
License-File: LICENSE
